{
  "_fv": 39,
  "_type": "recipe",
  "definition": {
    "recipeType": "Crafting",
    "xpReward": 0.0,
    "cookingTime": 200,
    "recipeRetstackSize": 1,
    "group": "",
    "recipeShapeless": true,
    "recipeSlots": [
      {
        "value": "Items.QUARTZ"
      },
      {
        "value": "Items.FLINT"
      },
      {
        "value": "Items.AMETHYST_SHARD"
      },
      {
        "value": "Items.HONEYCOMB"
      },
      {
        "value": "Items.DIAMOND"
      },
      {
        "value": "Items.NETHER_WART"
      },
      {
        "value": "Items.DYE#3"
      },
      {
        "value": "Items.GOLD_INGOT"
      },
      {
        "value": "Items.WHEAT"
      }
    ],
    "recipeReturnStack": {
      "value": "CUSTOM:FlintWrecker"
    },
    "name": "flint_wrecker_craft",
    "namespace": "mod"
  }
}